[{"ma":"VT","g":"4tr586k","me":"M","so":"976731762"},{"ma":"VT","g":"5tr886k","me":"M","so":"987394414"},{"ma":"VT","g":"5tr286k","me":"K","so":"985752655"},{"ma":"VT","g":"5tr886k","me":"T","so":"976833593"},{"ma":"VT","g":"4tr886k","me":"T","so":"966552149"},{"ma":"VT","g":"5tr686k","me":"M","so":"976558935"},{"ma":"VT","g":"5tr586k","me":"T","so":"965582687"},{"ma":"VT","g":"4tr786k","me":"K","so":"987287577"},{"ma":"VT","g":"4tr586k","me":"M","so":"975855622"},{"ma":"VT","g":"5tr286k","so":"965879353"},{"ma":"VT","g":"5tr586k","me":"T","so":"986947877"},{"ma":"VT","g":"8tr586k","me":"H","so":"972525627"},{"ma":"VT","g":"5tr286k","me":"T","so":"976933472"},{"ma":"VT","g":"5tr886k","me":"K","so":"982645395"},{"ma":"VT","g":"7tr286k","me":"H","so":"982768194"},{"ma":"VT","g":"6tr786k","so":"986414527"},{"ma":"VT","g":"5tr586k","me":"H","so":"967721544"},{"ma":"VT","g":"6tr586k","me":"K","so":"966853167"},{"ma":"VT","g":"6tr586k","me":"T","so":"985713872"},{"ma":"VT","g":"5tr886k","me":"T","so":"967653167"}]