[{"ma":"VT","g":"5tr686k","me":"K","so":"985663914"},{"ma":"VT","g":"5tr286k","me":"K","so":"976434667"},{"ma":"VT","g":"5tr286k","me":"T","so":"972575228"},{"ma":"VT","g":"8tr286k","me":"T","so":"986622311"},{"ma":"VT","g":"8tr586k","me":"TH","so":"987856993"},{"ma":"VT","g":"12tr686k","me":"T","so":"976331459"},{"ma":"VT","g":"6tr586k","me":"H","so":"987942627"},{"ma":"VT","g":"6tr586k","me":"TH","so":"972857134"},{"ma":"VT","g":"5tr886k","me":"T","so":"972419762"},{"ma":"VT","g":"6tr586k","so":"968557413"},{"ma":"VT","g":"6tr586k","me":"T","so":"985256513"},{"ma":"VT","g":"8tr686k","me":"T","so":"982893752"},{"ma":"VT","g":"5tr586k","me":"M","so":"962413662"},{"ma":"VT","g":"8tr686k","me":"M","so":"976252675"},{"ma":"VT","g":"5tr286k","me":"H","so":"967149657"},{"ma":"VT","g":"5tr886k","me":"K","so":"987866359"},{"ma":"VT","g":"4tr386k","me":"T","so":"977729411"},{"ma":"VT","g":"4tr386k","me":"M","so":"965256249"},{"ma":"VT","g":"5tr386k","me":"H","so":"966841227"},{"ma":"VT","g":"4tr986k","me":"T","so":"978251549"}]